revoltapi/__init__.py
revoltapi/api/__init__.py
revoltapi/api/api.py
revoltapi/api/excetions.py
revoltapi-0.1.0.dev1.dist-info/LICENSE
revoltapi-0.1.0.dev1.dist-info/METADATA
revoltapi-0.1.0.dev1.dist-info/WHEEL
revoltapi-0.1.0.dev1.dist-info/RECORD
