Metadata-Version: 2.1
Name: revoltapi
Version: 0.1.0.dev1
Summary: Library for working with the Revolt API.
Home-page: https://github.com/romanin-rf/RevoltAPI
License: GPL-3.0-only
Keywords: revoltapi,revolt,api,asyncio,async
Author: Romanin
Author-email: semina054@gmail.com
Requires-Python: >=3.9,<3.12
Classifier: Environment :: Web Environment
Classifier: License :: OSI Approved :: GNU Affero General Public License v3
Classifier: License :: OSI Approved :: GNU General Public License v3 (GPLv3)
Classifier: Operating System :: MacOS :: MacOS X
Classifier: Operating System :: Microsoft :: Windows
Classifier: Operating System :: POSIX :: Linux
Classifier: Operating System :: Unix
Classifier: Programming Language :: Python :: 3
Classifier: Programming Language :: Python :: 3.9
Classifier: Programming Language :: Python :: 3.10
Classifier: Programming Language :: Python :: 3.11
Classifier: Programming Language :: Python :: 3 :: Only
Requires-Dist: asyncio (>=3.4.3,<4.0.0)
Requires-Dist: httpx (>=0.24.1,<0.25.0)
Requires-Dist: nest-asyncio (>=1.5.6,<2.0.0)
Requires-Dist: requests (>=2.31.0,<3.0.0)
Requires-Dist: websockets (>=11.0.3,<12.0.0)
Project-URL: Repository, https://github.com/romanin-rf/RevoltAPI
